alas_ce0_openpyxl-0.1.dist-info/DESCRIPTION.rst
alas_ce0_openpyxl-0.1.dist-info/METADATA
alas_ce0_openpyxl-0.1.dist-info/RECORD
alas_ce0_openpyxl-0.1.dist-info/WHEEL
alas_ce0_openpyxl-0.1.dist-info/metadata.json
alas_ce0_openpyxl-0.1.dist-info/top_level.txt
openpyxl/__init__.py
openpyxl/conftest.py
openpyxl/cell/__init__.py
openpyxl/cell/cell.py
openpyxl/cell/interface.py
openpyxl/cell/read_only.py
openpyxl/cell/text.py
openpyxl/cell/tests/__init__.py
openpyxl/cell/tests/test_cell.py
openpyxl/cell/tests/test_read_only.py
openpyxl/cell/tests/test_text.py
openpyxl/chart/_3d.py
openpyxl/chart/__init__.py
openpyxl/chart/_chart.py
openpyxl/chart/area_chart.py
openpyxl/chart/axis.py
openpyxl/chart/bar_chart.py
openpyxl/chart/bubble_chart.py
openpyxl/chart/chartspace.py
openpyxl/chart/data_source.py
openpyxl/chart/descriptors.py
openpyxl/chart/error_bar.py
openpyxl/chart/label.py
openpyxl/chart/layout.py
openpyxl/chart/legend.py
openpyxl/chart/line_chart.py
openpyxl/chart/marker.py
openpyxl/chart/picture.py
openpyxl/chart/pie_chart.py
openpyxl/chart/print_settings.py
openpyxl/chart/radar_chart.py
openpyxl/chart/reader.py
openpyxl/chart/reference.py
openpyxl/chart/scatter_chart.py
openpyxl/chart/series.py
openpyxl/chart/series_factory.py
openpyxl/chart/shapes.py
openpyxl/chart/stock_chart.py
openpyxl/chart/surface_chart.py
openpyxl/chart/text.py
openpyxl/chart/title.py
openpyxl/chart/trendline.py
openpyxl/chart/updown_bars.py
openpyxl/chart/tests/__init__.py
openpyxl/chart/tests/conftest.py
openpyxl/chart/tests/test_area_chart.py
openpyxl/chart/tests/test_axis.py
openpyxl/chart/tests/test_bar_chart.py
openpyxl/chart/tests/test_bubble_chart.py
openpyxl/chart/tests/test_chart.py
openpyxl/chart/tests/test_chartspace.py
openpyxl/chart/tests/test_data_source.py
openpyxl/chart/tests/test_error_bar.py
openpyxl/chart/tests/test_label.py
openpyxl/chart/tests/test_layout.py
openpyxl/chart/tests/test_legend.py
openpyxl/chart/tests/test_line_chart.py
openpyxl/chart/tests/test_marker.py
openpyxl/chart/tests/test_picture.py
openpyxl/chart/tests/test_pie_chart.py
openpyxl/chart/tests/test_print.py
openpyxl/chart/tests/test_radar_chart.py
openpyxl/chart/tests/test_reader.py
