Metadata-Version: 2.0
Name: alas-ce0-openpyxl
Version: 0.1
Summary: A Python library to read/write Excel 2010 xlsx/xlsm files for ALAS-Ce0
Home-page: https://pypi.python.org/pypi/alas-ce0-openpyxl
Author: Adonis Cesar Legón Campo
Author-email: alegon@alasxpress.com
License: MIT
Platform: UNKNOWN
Classifier: Development Status :: 5 - Production/Stable
Classifier: Operating System :: MacOS :: MacOS X
Classifier: Operating System :: Microsoft :: Windows
Classifier: Operating System :: POSIX
Classifier: License :: OSI Approved :: MIT License
Classifier: Programming Language :: Python
Classifier: Programming Language :: Python :: 2.6
Classifier: Programming Language :: Python :: 2.7
Classifier: Programming Language :: Python :: 3.3
Classifier: Programming Language :: Python :: 3.4
Classifier: Programming Language :: Python :: 3.5
Classifier: Programming Language :: Python :: 3.6
Requires: python (>=2.6.0)
Requires-Dist: et-xmlfile
Requires-Dist: jdcal
